setup.py
ddots_client/__init__.py
ddots_client/api_client.py
ddots_client/configuration.py
ddots_client/rest.py
ddots_client.egg-info/PKG-INFO
ddots_client.egg-info/SOURCES.txt
ddots_client.egg-info/dependency_links.txt
ddots_client.egg-info/requires.txt
ddots_client.egg-info/top_level.txt
ddots_client/apis/__init__.py
ddots_client/apis/auth_api.py
ddots_client/apis/problems_api.py
ddots_client/apis/programming_languages_api.py
ddots_client/apis/solutions_api.py
ddots_client/apis/teams_api.py
ddots_client/apis/users_api.py
ddots_client/models/__init__.py
ddots_client/models/base_o_auth2_client.py
ddots_client/models/base_problem.py
ddots_client/models/base_programming_language.py
ddots_client/models/base_solution.py
ddots_client/models/base_solution_author.py
ddots_client/models/base_solution_problem.py
ddots_client/models/base_solution_programming_language.py
ddots_client/models/base_team.py
ddots_client/models/base_team_member.py
ddots_client/models/base_team_member_team.py
ddots_client/models/base_user.py
ddots_client/models/body.py
ddots_client/models/body_1.py
ddots_client/models/body_2.py
ddots_client/models/body_3.py
ddots_client/models/body_4.py
ddots_client/models/detailed_o_auth2_client.py
ddots_client/models/detailed_problem.py
ddots_client/models/detailed_programming_language.py
ddots_client/models/detailed_solution.py
ddots_client/models/detailed_solution_testing_report.py
ddots_client/models/detailed_team.py
ddots_client/models/detailed_team_members.py
ddots_client/models/detailed_user.py
ddots_client/models/http_error401.py
ddots_client/models/http_error403.py
ddots_client/models/http_error404.py
ddots_client/models/http_error409.py
ddots_client/models/http_error422.py
ddots_client/models/problem_tests_archive_schema.py
ddots_client/models/solution_source_code_schema.py
ddots_client/models/solutionssolution_idtestingreport_tests.py
ddots_client/models/testing_solution.py
ddots_client/models/testing_solution_programming_language.py
ddots_client/models/user_signup_form.py
test/__init__.py
test/test_auth_api.py
test/test_base_o_auth2_client.py
test/test_base_problem.py
test/test_base_programming_language.py
