Metadata-Version: 1.0
Name: ddots-client
Version: 0.1.1
Summary: DDOTS RESTful API Server
Home-page: UNKNOWN
Author: UNKNOWN
Author-email: UNKNOWN
License: UNKNOWN
Keywords: Swagger,DDOTS RESTful API Server
Platform: UNKNOWN
